Metadata-Version: 2.4
Name: torchsort
Version: 0.1.10
Summary: Differentiable sorting and ranking in PyTorch
Home-page: https://github.com/teddykoker/torchsort
Author: Teddy Koker
License:                                  Apache License
Project-URL: Homepage, https://github.com/teddykoker/torchsort
Project-URL: Repository, https://github.com/teddykoker/torchsort
Project-URL: Bug Tracker, https://github.com/teddykoker/torchsort/issues
Classifier: Programming Language :: Python :: 3
Requires-Python: >=3.7
License-File: LICENSE
Requires-Dist: torch>=1.7.1
Dynamic: home-page
Dynamic: license-file
Dynamic: requires-python
